dockit/__init__.py
dockit/cli.py
dockit/commands/__init__.py
dockit/commands/clean.py
dockit/commands/down.py
dockit/commands/logs.py
dockit/commands/ps.py
dockit/commands/restart.py
dockit/commands/shell.py
dockit/commands/up.py
dockit/commands/version.py
dockit/core/__init__.py
dockit/core/autocomplete.py
dockit/core/compose.py
dockit/core/detect.py
dockit/core/docker.py
dockit/core/errors.py
dockit/core/output.py
dockit/core/utils.py
dockit_tool-0.1.2.dist-info/licenses/LICENSE
dockit_tool-0.1.2.dist-info/METADATA
dockit_tool-0.1.2.dist-info/WHEEL
dockit_tool-0.1.2.dist-info/entry_points.txt
dockit_tool-0.1.2.dist-info/top_level.txt
dockit_tool-0.1.2.dist-info/RECORD
