Metadata-Version: 2.4
Name: dockit-tool
Version: 0.1.2
Summary: A production-grade Docker wrapper CLI focused on usability and simplicity
Author-email: Mauro Alexandre <profissionalweb04@gmail.com>
License: MIT
Project-URL: Homepage, https://github.com/developerdevice/Dockit
Project-URL: Repository, https://github.com/developerdevice/Dockit
Project-URL: Issues, https://github.com/developerdevice/Dockit/issues
Requires-Python: >=3.9
License-File: LICENSE
Requires-Dist: typer[all]>=0.9.0
Requires-Dist: rich>=13.0.0
Requires-Dist: pydantic>=2.0.0
Provides-Extra: dev
Requires-Dist: pytest>=7.0.0; extra == "dev"
Requires-Dist: pytest-cov>=4.0.0; extra == "dev"
Requires-Dist: black>=23.0.0; extra == "dev"
Requires-Dist: ruff>=0.1.0; extra == "dev"
Requires-Dist: bandit>=1.7.0; extra == "dev"
Provides-Extra: test
Requires-Dist: pytest>=7.0.0; extra == "test"
Requires-Dist: pytest-cov>=4.0.0; extra == "test"
Provides-Extra: lint
Requires-Dist: black>=23.0.0; extra == "lint"
Requires-Dist: ruff>=0.1.0; extra == "lint"
Dynamic: license-file
